onlinehd/__init__.py
onlinehd/encoder.py
onlinehd/fasthd/onlinehd.cpp
onlinehd/onlinehd.py
onlinehd/spatial.py
onlinehd-0.1.2.dist-info/LICENSE
onlinehd-0.1.2.dist-info/WHEEL
onlinehd-0.1.2.dist-info/METADATA
onlinehd-0.1.2.dist-info/RECORD
