Metadata-Version: 2.1
Name: onlinehd
Version: 0.1.2
Summary: Efficient single-pass hyperdimensional classifier
Home-page: https://gitlab.com/biaslab/onlinehd
License: MIT
Author: alehd
Author-email: ale.hdz333@ciencias.unam.mx
Requires-Python: >=3.8,<4.0
Classifier: License :: OSI Approved :: MIT License
Classifier: Programming Language :: Python :: 3
Classifier: Programming Language :: Python :: 3.8
Classifier: Programming Language :: Python :: 3.9
Requires-Dist: ninja (>=1.10.0,<2.0.0)
Requires-Dist: torch (>=1.7.1,<2.0.0)
Project-URL: Repository, https://gitlab.com/biaslab/onlinehd
